valid8r/__init__.py
valid8r/_version.py
valid8r/async_validators.py
valid8r/core/__init__.py
valid8r/core/combinators.py
valid8r/core/errors.py
valid8r/core/maybe.py
valid8r/core/parsers.py
valid8r/core/schema.py
valid8r/core/type_adapters.py
valid8r/core/validators.py
valid8r/integrations/__init__.py
valid8r/integrations/argparse.py
valid8r/integrations/click.py
valid8r/integrations/env.py
valid8r/integrations/pydantic.py
valid8r/integrations/typer.py
valid8r/prompt/__init__.py
valid8r/prompt/basic.py
valid8r/prompt/io_provider.py
valid8r/testing/__init__.py
valid8r/testing/assertions.py
valid8r/testing/generators.py
valid8r/testing/mock_input.py
valid8r/py.typed
valid8r-1.30.0.dist-info/METADATA
valid8r-1.30.0.dist-info/WHEEL
valid8r-1.30.0.dist-info/entry_points.txt
valid8r-1.30.0.dist-info/licenses/LICENSE
valid8r-1.30.0.dist-info/RECORD
