Metadata-Version: 2.4
Name: valid8r
Version: 1.30.0
Summary: Clean, flexible input validation for Python applications
Project-URL: Homepage, https://valid8r.readthedocs.io/
Project-URL: Repository, https://github.com/mikelane/valid8r
Project-URL: Documentation, https://valid8r.readthedocs.io/
Project-URL: Issues, https://github.com/mikelane/valid8r/issues
Author-email: Mike Lane <mikelane@gmail.com>
License: MIT
License-File: LICENSE
Keywords: cli,functional-programming,input,maybe-monad,parsing,validation
Classifier: Development Status :: 5 - Production/Stable
Classifier: Intended Audience :: Developers
Classifier: License :: OSI Approved :: MIT License
Classifier: Operating System :: OS Independent
Classifier: Programming Language :: Python :: 3
Classifier: Programming Language :: Python :: 3.11
Classifier: Programming Language :: Python :: 3.12
Classifier: Programming Language :: Python :: 3.13
Classifier: Programming Language :: Python :: 3.14
Classifier: Topic :: Software Development :: Libraries :: Python Modules
Classifier: Topic :: Software Development :: Quality Assurance
Classifier: Typing :: Typed
Requires-Python: >=3.11
Requires-Dist: email-validator>=2.3.0
Requires-Dist: pydantic-core>=2.27.0
Requires-Dist: pydantic>=2.0
Requires-Dist: uuid-utils>=0.11.0
Provides-Extra: click
Requires-Dist: click>=8.0.0; extra == 'click'
Provides-Extra: typer
Requires-Dist: typer>=0.20.0; extra == 'typer'
